{
  "jest": {
    "services": {
      "ceramic": {
        "mode": "node",
        "anchorServiceAPI": "https://cas-dev.3boxlabs.com",
        "ethereumRpc": "@@ETH_RPC_URL",
        "s3StateStoreBucketName": "ceramic-dev-tests/node",
        "network": "dev-unstable"
      },
      "ipfs": {
        "mode": "client",
        "apiURL": "http://localhost:5011"
      },
      "ceramicClient": {
        "mode": "client",
        "apiURL": "https://ceramic-private-dev.3boxlabs.com"
      }
    }
  },
  "serviceLauncher": {
    "services": [
      {
        "type": "ipfs",
        "port": 5011
      }
    ]
  }
}
